sni_requests.py
sni_requests/sni_requests.py
sni_requests-0.1.2.dist-info/METADATA
sni_requests-0.1.2.dist-info/WHEEL
sni_requests-0.1.2.dist-info/top_level.txt
sni_requests-0.1.2.dist-info/RECORD
