Metadata-Version: 2.4
Name: sni_requests
Version: 0.1.2
Summary: A requests wrapper that allows setting a custom SNI hostname for HTTPS connections
Home-page: https://github.com/42zen/sni_requests
Author: hacked_by_zen
Requires-Dist: requests
Requires-Dist: urllib3
Dynamic: author
Dynamic: description
Dynamic: description-content-type
Dynamic: home-page
Dynamic: requires-dist
Dynamic: summary
